asyncio_atexit.py
asyncio_atexit-1.0.1.dist-info/LICENSE
asyncio_atexit-1.0.1.dist-info/METADATA
asyncio_atexit-1.0.1.dist-info/WHEEL
asyncio_atexit-1.0.1.dist-info/top_level.txt
asyncio_atexit-1.0.1.dist-info/RECORD
