Metadata-Version: 2.1
Name: asyncio-atexit
Version: 1.0.1
Summary: Like atexit, but for asyncio
Home-page: https://github.com/minrk/asyncio-atexit
Author: Min RK
Author-email: benjaminrk@gmail.com
License: MIT License
Keywords: asyncio
Platform: UNKNOWN
Classifier: Framework :: AsyncIO
Classifier: License :: OSI Approved :: MIT License
Classifier: Programming Language :: Python :: 3
Classifier: Programming Language :: Python :: 3.6
Requires-Python: >=3.6
Provides-Extra: test
License-File: LICENSE
